{
    "RPI3_32": {
        "4": {
            "avg_times": 345,
            "failure_ratio": 0.0
        },
        "8": {
            "avg_times": 389,
            "failure_ratio": 0.0
        },
        "12": {
            "avg_times": 461,
            "failure_ratio": 0.0
        },
        "16": {
            "avg_times": 544,
            "failure_ratio": 0.23
        },
        "20": {
            "avg_times": 612,
            "failure_ratio": 7.07
        }
    },
    "RPI4_32": {
        "4": {
            "avg_times": 374,
            "failure_ratio": 0.0
        },
        "8": {
            "avg_times": 446,
            "failure_ratio": 1.31
        },
        "12": {
            "avg_times": 504,
            "failure_ratio": 0.29
        },
        "16": {
            "avg_times": 598,
            "failure_ratio": 36.28
        },
        "20": {
            "avg_times": 628,
            "failure_ratio": 37.06
        }
    },
    "RPI4_32_2": {
        "4": {
            "avg_times": 370,
            "failure_ratio": 0,
            "nb_deployments": 44
        },
        "8": {
            "avg_times": 439,
            "failure_ratio": 0,
            "nb_deployments": 44
        },
        "12": {
            "avg_times": 504,
            "failure_ratio": 1,
            "nb_deployments": 44
        },
        "16": {
            "avg_times": 571,
            "failure_ratio": 6,
            "nb_deployments": 36
        },
        "20": {
            "avg_times": 629,
            "failure_ratio": 12,
            "nb_deployments": 27
        }
    },
    "RPI4_32_SDCARD":{
        "4": {
            "avg_times": 386,
            "failure_ratio": 0,
            "nb_deployments": 21
        },
        "8": {
            "avg_times": 479,
            "failure_ratio": 1,
            "nb_deployments": 21
        },
        "12": {
            "avg_times": 553,
            "failure_ratio": 4,
            "nb_deployments": 21
        },
        "16": {
            "avg_times": 628,
            "failure_ratio": 15,
            "nb_deployments": 12
        },
        "20": {
            "avg_times": 695,
            "failure_ratio": 17,
            "nb_deployments": 7
        }
    },
    "RPI4_64": {
        "4": {
            "avg_times": 357,
            "failure_ratio": 0.0
        },
        "8": {
            "avg_times": 401,
            "failure_ratio": 0.0
        },
        "12": {
            "avg_times": 465,
            "failure_ratio": 0.0
        },
        "16": {
            "avg_times": 534,
            "failure_ratio": 10.34
        },
        "20": {
            "avg_times": 600,
            "failure_ratio": 8.11
        }
    },
    "VM": {
        "4": {
            "avg_times": 326,
            "failure_ratio": 0
        },
        "8": {
            "avg_times": 355,
            "failure_ratio": 2
        },
        "12": {
            "avg_times": 391,
            "failure_ratio": 0
        },
        "16": {
            "avg_times": 425,
            "failure_ratio": 0
        },
        "20": {
            "avg_times": 454,
            "failure_ratio": 0
        }
    }
}
