{
    "raspbian_buster_32bit": {
        "node-1": [
            {
                "ip": "192.168.1.51",
                "start_date": "2020-09-03 20:48:00.188351",
                "states": {
                    "last_state": "deployed",
                    "last_date": "2020-09-03 20:57:00",
                    "nfs_boot_conf": 1.0,
                    "nfs_boot_off": 4.0,
                    "nfs_boot_on": 9.0,
                    "env_copy": 48.0,
                    "env_check": 269.0,
                    "delete_partition": 21.0,
                    "create_partition": 17.0,
                    "mount_partition": 19.0,
                    "resize_partition": 17.0,
                    "wait_resizing": 16.0,
                    "system_conf": 18.0,
                    "user_conf": 65.0,
                    "user_script": 36.0
                },
                "total": 540.0,
                "ping": true,
                "ssh": true,
                "init_script": true
            }
        ],
        "node-2": [
            {
                "ip": "192.168.1.52",
                "start_date": "2020-09-03 20:48:00.189177",
                "states": {
                    "last_state": "deployed",
                    "last_date": "2020-09-03 20:59:01",
                    "nfs_boot_conf": 1.0,
                    "nfs_boot_off": 4.0,
                    "nfs_boot_on": 10.0,
                    "env_copy": 74.0,
                    "env_check": 326.0,
                    "delete_partition": 14.0,
                    "create_partition": 69.0,
                    "mount_partition": 37.0,
                    "resize_partition": 45.0,
                    "wait_resizing": 14.0,
                    "system_conf": 17.0,
                    "user_conf": 43.0,
                    "user_script": 7.0
                },
                "total": 661.0,
                "ping": true,
                "ssh": true,
                "init_script": true
            }
        ],
        "node-3": [
            {
                "ip": "192.168.1.53",
                "start_date": "2020-09-03 20:48:00.189814",
                "states": {
                    "last_state": "deployed",
                    "last_date": "2020-09-03 20:59:11",
                    "nfs_boot_conf": 1.0,
                    "nfs_boot_off": 4.0,
                    "nfs_boot_on": 10.0,
                    "env_copy": 75.0,
                    "env_check": 326.0,
                    "delete_partition": 13.0,
                    "create_partition": 70.0,
                    "mount_partition": 37.0,
                    "resize_partition": 44.0,
                    "wait_resizing": 15.0,
                    "system_conf": 26.0,
                    "user_conf": 46.0,
                    "user_script": 4.0
                },
                "total": 671.0,
                "ping": true,
                "ssh": true,
                "init_script": true
            }
        ],
        "node-4": [
            {
                "ip": "192.168.1.54",
                "start_date": "2020-09-03 20:48:00.190418",
                "states": {
                    "last_state": "deployed",
                    "last_date": "2020-09-03 20:57:01",
                    "nfs_boot_conf": 1.0,
                    "nfs_boot_off": 4.0,
                    "nfs_boot_on": 11.0,
                    "env_copy": 47.0,
                    "env_check": 272.0,
                    "delete_partition": 18.0,
                    "create_partition": 17.0,
                    "mount_partition": 18.0,
                    "resize_partition": 17.0,
                    "wait_resizing": 16.0,
                    "system_conf": 25.0,
                    "user_conf": 59.0,
                    "user_script": 36.0
                },
                "total": 541.0,
                "ping": true,
                "ssh": true,
                "init_script": true
            }
        ],
        "node-5": [
            {
                "ip": "192.168.1.55",
                "start_date": "2020-09-03 20:48:00.191023",
                "states": {
                    "last_state": "deployed",
                    "last_date": "2020-09-03 20:57:01",
                    "nfs_boot_conf": 1.0,
                    "nfs_boot_off": 5.0,
                    "nfs_boot_on": 10.0,
                    "env_copy": 48.0,
                    "env_check": 272.0,
                    "delete_partition": 17.0,
                    "create_partition": 18.0,
                    "mount_partition": 18.0,
                    "resize_partition": 16.0,
                    "wait_resizing": 16.0,
                    "system_conf": 31.0,
                    "user_conf": 53.0,
                    "user_script": 36.0
                },
                "total": 541.0,
                "ping": true,
                "ssh": true,
                "init_script": true
            }
        ],
        "node-7": [
            {
                "ip": "192.168.1.57",
                "start_date": "2020-09-03 20:48:00.191618",
                "states": {
                    "last_state": "deployed",
                    "last_date": "2020-09-03 20:57:02",
                    "nfs_boot_conf": 1.0,
                    "nfs_boot_off": 5.0,
                    "nfs_boot_on": 11.0,
                    "env_copy": 49.0,
                    "env_check": 270.0,
                    "delete_partition": 18.0,
                    "create_partition": 18.0,
                    "mount_partition": 18.0,
                    "resize_partition": 16.0,
                    "wait_resizing": 16.0,
                    "system_conf": 37.0,
                    "user_conf": 47.0,
                    "user_script": 36.0
                },
                "total": 542.0,
                "ping": true,
                "ssh": true,
                "init_script": true
            }
        ],
        "node-8": [
            {
                "ip": "192.168.1.58",
                "start_date": "2020-09-03 20:48:00.192216",
                "states": {
                    "last_state": "deployed",
                    "last_date": "2020-09-03 20:58:26",
                    "nfs_boot_conf": 1.0,
                    "nfs_boot_off": 5.0,
                    "nfs_boot_on": 11.0,
                    "env_copy": 73.0,
                    "env_check": 290.0,
                    "delete_partition": 17.0,
                    "create_partition": 13.0,
                    "mount_partition": 15.0,
                    "resize_partition": 70.0,
                    "wait_resizing": 38.0,
                    "system_conf": 21.0,
                    "user_conf": 48.0,
                    "user_script": 24.0
                },
                "total": 626.0,
                "ping": true,
                "ssh": true,
                "init_script": true
            }
        ],
        "node-9": [
            {
                "ip": "192.168.1.59",
                "start_date": "2020-09-03 20:48:00.192818",
                "states": {
                    "last_state": "deployed",
                    "last_date": "2020-09-03 20:58:00",
                    "nfs_boot_conf": 1.0,
                    "nfs_boot_off": 6.0,
                    "nfs_boot_on": 11.0,
                    "env_copy": 73.0,
                    "env_check": 269.0,
                    "delete_partition": 18.0,
                    "create_partition": 16.0,
                    "mount_partition": 14.0,
                    "resize_partition": 16.0,
                    "wait_resizing": 70.0,
                    "system_conf": 23.0,
                    "user_conf": 70.0,
                    "user_script": 13.0
                },
                "total": 600.0,
                "ping": true,
                "ssh": true,
                "init_script": true
            }
        ],
        "node-12": [
            {
                "ip": "192.168.1.62",
                "start_date": "2020-09-03 20:48:00.193417",
                "states": {
                    "last_state": "deployed",
                    "last_date": "2020-09-03 20:58:27",
                    "nfs_boot_conf": 1.0,
                    "nfs_boot_off": 6.0,
                    "nfs_boot_on": 11.0,
                    "env_copy": 51.0,
                    "env_check": 312.0,
                    "delete_partition": 16.0,
                    "create_partition": 14.0,
                    "mount_partition": 15.0,
                    "resize_partition": 69.0,
                    "wait_resizing": 39.0,
                    "system_conf": 26.0,
                    "user_conf": 42.0,
                    "user_script": 25.0
                },
                "total": 627.0,
                "ping": true,
                "ssh": true,
                "init_script": true
            }
        ],
        "node-14": [
            {
                "ip": "192.168.1.64",
                "start_date": "2020-09-03 20:48:00.194008",
                "states": {
                    "last_state": "deployed",
                    "last_date": "2020-09-03 20:58:37",
                    "nfs_boot_conf": 1.0,
                    "nfs_boot_off": 6.0,
                    "nfs_boot_on": 12.0,
                    "env_copy": 52.0,
                    "env_check": 310.0,
                    "delete_partition": 17.0,
                    "create_partition": 15.0,
                    "mount_partition": 14.0,
                    "resize_partition": 69.0,
                    "wait_resizing": 38.0,
                    "system_conf": 33.0,
                    "user_conf": 63.0,
                    "user_script": 7.0
                },
                "total": 637.0,
                "ping": true,
                "ssh": true,
                "init_script": true
            }
        ],
        "node-15": [
            {
                "ip": "192.168.1.65",
                "start_date": "2020-09-03 20:48:00.194600",
                "states": {
                    "last_state": "deployed",
                    "last_date": "2020-09-03 20:58:37",
                    "nfs_boot_conf": 1.0,
                    "nfs_boot_off": 7.0,
                    "nfs_boot_on": 11.0,
                    "env_copy": 73.0,
                    "env_check": 290.0,
                    "delete_partition": 16.0,
                    "create_partition": 16.0,
                    "mount_partition": 13.0,
                    "resize_partition": 69.0,
                    "wait_resizing": 38.0,
                    "system_conf": 40.0,
                    "user_conf": 56.0,
                    "user_script": 7.0
                },
                "total": 637.0,
                "ping": true,
                "ssh": true,
                "init_script": true
            }
        ],
        "node-16": [
            {
                "ip": "192.168.1.66",
                "start_date": "2020-09-03 20:48:00.195189",
                "states": {
                    "last_state": "deployed",
                    "last_date": "2020-09-03 20:58:38",
                    "nfs_boot_conf": 1.0,
                    "nfs_boot_off": 7.0,
                    "nfs_boot_on": 12.0,
                    "env_copy": 74.0,
                    "env_check": 288.0,
                    "delete_partition": 16.0,
                    "create_partition": 17.0,
                    "mount_partition": 13.0,
                    "resize_partition": 68.0,
                    "wait_resizing": 39.0,
                    "system_conf": 44.0,
                    "user_conf": 52.0,
                    "user_script": 7.0
                },
                "total": 638.0,
                "ping": true,
                "ssh": true,
                "init_script": true
            }
        ],
        "node-17": [
            {
                "ip": "192.168.1.67",
                "start_date": "2020-09-03 20:48:00.195793",
                "states": {
                    "last_state": "deployed",
                    "last_date": "2020-09-03 20:59:17",
                    "nfs_boot_conf": 1.0,
                    "nfs_boot_off": 7.0,
                    "nfs_boot_on": 12.0,
                    "env_copy": 52.0,
                    "env_check": 270.0,
                    "delete_partition": 12.0,
                    "create_partition": 19.0,
                    "mount_partition": 17.0,
                    "resize_partition": 16.0,
                    "wait_resizing": 16.0,
                    "system_conf": 46.0,
                    "user_conf": 5.0,
                    "off_requested": 128.0,
                    "on_requested": 26.0,
                    "rebooting": 45.0,
                    "user_script": 5.0
                },
                "total": 677.0,
                "ping": true,
                "ssh": true,
                "init_script": true
            }
        ],
        "node-18": [
            {
                "ip": "192.168.1.68",
                "start_date": "2020-09-03 20:48:00.196390",
                "states": {
                    "last_state": "deployed",
                    "last_date": "2020-09-03 20:59:17",
                    "nfs_boot_conf": 1.0,
                    "nfs_boot_off": 8.0,
                    "nfs_boot_on": 12.0,
                    "env_copy": 52.0,
                    "env_check": 270.0,
                    "delete_partition": 12.0,
                    "create_partition": 19.0,
                    "mount_partition": 17.0,
                    "resize_partition": 15.0,
                    "wait_resizing": 16.0,
                    "system_conf": 51.0,
                    "user_conf": 4.0,
                    "off_requested": 123.0,
                    "on_requested": 27.0,
                    "rebooting": 45.0,
                    "user_script": 5.0
                },
                "total": 677.0,
                "ping": true,
                "ssh": true,
                "init_script": true
            }
        ],
        "node-19": [
            {
                "ip": "192.168.1.69",
                "start_date": "2020-09-03 20:48:00.196992",
                "states": {
                    "last_state": "deployed",
                    "last_date": "2020-09-03 20:58:00",
                    "nfs_boot_conf": 1.0,
                    "nfs_boot_off": 8.0,
                    "nfs_boot_on": 12.0,
                    "env_copy": 75.0,
                    "env_check": 267.0,
                    "delete_partition": 15.0,
                    "create_partition": 17.0,
                    "mount_partition": 14.0,
                    "resize_partition": 15.0,
                    "wait_resizing": 70.0,
                    "system_conf": 29.0,
                    "user_conf": 70.0,
                    "user_script": 7.0
                },
                "total": 600.0,
                "ping": true,
                "ssh": true,
                "init_script": true
            }
        ],
        "node-20": [
            {
                "ip": "192.168.1.70",
                "start_date": "2020-09-03 20:48:00.197590",
                "states": {
                    "last_state": "deployed",
                    "last_date": "2020-09-03 20:57:44",
                    "nfs_boot_conf": 1.0,
                    "nfs_boot_off": 8.0,
                    "nfs_boot_on": 13.0,
                    "env_copy": 53.0,
                    "env_check": 269.0,
                    "delete_partition": 12.0,
                    "create_partition": 19.0,
                    "mount_partition": 17.0,
                    "resize_partition": 15.0,
                    "wait_resizing": 16.0,
                    "system_conf": 59.0,
                    "user_conf": 65.0,
                    "user_script": 37.0
                },
                "total": 584.0,
                "ping": true,
                "ssh": true,
                "init_script": true
            }
        ],
        "node-21": [
            {
                "ip": "192.168.1.71",
                "start_date": "2020-09-03 20:48:00.198192",
                "states": {
                    "last_state": "deployed",
                    "last_date": "2020-09-03 20:58:01",
                    "nfs_boot_conf": 1.0,
                    "nfs_boot_off": 9.0,
                    "nfs_boot_on": 12.0,
                    "env_copy": 54.0,
                    "env_check": 287.0,
                    "delete_partition": 16.0,
                    "create_partition": 17.0,
                    "mount_partition": 13.0,
                    "resize_partition": 16.0,
                    "wait_resizing": 70.0,
                    "system_conf": 38.0,
                    "user_conf": 61.0,
                    "user_script": 7.0
                },
                "total": 601.0,
                "ping": true,
                "ssh": true,
                "init_script": true
            }
        ],
        "node-22": [
            {
                "ip": "192.168.1.72",
                "start_date": "2020-09-03 20:48:00.198796",
                "states": {
                    "last_state": "rebooting",
                    "last_date": "2020-09-03 20:50:31",
                    "nfs_boot_conf": 1.0,
                    "nfs_boot_off": 9.0,
                    "nfs_boot_on": 13.0,
                    "env_copy": 0.0,
                    "off_requested": 103.0,
                    "on_requested": 25.0,
                    "rebooting": 180.95286
                },
                "total": 0,
                "ping": false,
                "ssh": false,
                "init_script": false
            }
        ],
        "node-23": [
            {
                "ip": "192.168.1.73",
                "start_date": "2020-09-03 20:48:00.199440",
                "states": {
                    "last_state": "deployed",
                    "last_date": "2020-09-03 20:57:45",
                    "nfs_boot_conf": 1.0,
                    "nfs_boot_off": 9.0,
                    "nfs_boot_on": 13.0,
                    "env_copy": 75.0,
                    "env_check": 248.0,
                    "delete_partition": 10.0,
                    "create_partition": 20.0,
                    "mount_partition": 16.0,
                    "resize_partition": 15.0,
                    "wait_resizing": 16.0,
                    "system_conf": 63.0,
                    "user_conf": 62.0,
                    "user_script": 37.0
                },
                "total": 585.0,
                "ping": true,
                "ssh": true,
                "init_script": true
            }
        ],
        "node-24": [
            {
                "ip": "192.168.1.74",
                "start_date": "2020-09-03 20:48:00.200040",
                "states": {
                    "last_state": "deployed",
                    "last_date": "2020-09-03 20:57:45",
                    "nfs_boot_conf": 1.0,
                    "nfs_boot_off": 9.0,
                    "nfs_boot_on": 13.0,
                    "env_copy": 77.0,
                    "env_check": 247.0,
                    "delete_partition": 10.0,
                    "create_partition": 20.0,
                    "mount_partition": 16.0,
                    "resize_partition": 14.0,
                    "wait_resizing": 16.0,
                    "system_conf": 69.0,
                    "user_conf": 57.0,
                    "user_script": 36.0
                },
                "total": 585.0,
                "ping": true,
                "ssh": true,
                "init_script": true
            }
        ]
    }
}