{
    "raspbian_buster_32bit": {
        "node-1": [
            {
                "ip": "192.168.1.51",
                "start_date": "2020-09-13 22:24:07.598529",
                "states": {
                    "last_state": "deployed",
                    "last_date": "2020-09-13 22:32:03",
                    "nfs_boot_conf": 2.0,
                    "nfs_boot_off": 4.0,
                    "nfs_boot_on": 7.0,
                    "env_copy": 37.0,
                    "env_check": 197.0,
                    "delete_partition": 17.0,
                    "create_partition": 10.0,
                    "mount_partition": 14.0,
                    "resize_partition": 15.0,
                    "wait_resizing": 9.0,
                    "system_conf": 25.0,
                    "user_conf": 68.0,
                    "user_script": 71.0
                },
                "total": 476.0,
                "ping": true,
                "ssh": true,
                "init_script": true
            }
        ],
        "node-2": [
            {
                "ip": "192.168.1.52",
                "start_date": "2020-09-13 22:24:07.599000",
                "states": {
                    "last_state": "deployed",
                    "last_date": "2020-09-13 22:32:15",
                    "nfs_boot_conf": 2.0,
                    "nfs_boot_off": 4.0,
                    "nfs_boot_on": 8.0,
                    "env_copy": 59.0,
                    "env_check": 194.0,
                    "delete_partition": 14.0,
                    "create_partition": 12.0,
                    "mount_partition": 12.0,
                    "resize_partition": 9.0,
                    "wait_resizing": 80.0,
                    "system_conf": 22.0,
                    "user_conf": 62.0,
                    "user_script": 10.0
                },
                "total": 488.0,
                "ping": true,
                "ssh": true,
                "init_script": true
            }
        ],
        "node-3": [
            {
                "ip": "192.168.1.53",
                "start_date": "2020-09-13 22:24:07.599408",
                "states": {
                    "last_state": "deployed",
                    "last_date": "2020-09-13 22:32:16",
                    "nfs_boot_conf": 2.0,
                    "nfs_boot_off": 4.0,
                    "nfs_boot_on": 8.0,
                    "env_copy": 60.0,
                    "env_check": 193.0,
                    "delete_partition": 15.0,
                    "create_partition": 12.0,
                    "mount_partition": 12.0,
                    "resize_partition": 9.0,
                    "wait_resizing": 80.0,
                    "system_conf": 38.0,
                    "user_conf": 46.0,
                    "user_script": 10.0
                },
                "total": 489.0,
                "ping": true,
                "ssh": true,
                "init_script": true
            }
        ],
        "node-4": [
            {
                "ip": "192.168.1.54",
                "start_date": "2020-09-13 22:24:07.599765",
                "states": {
                    "last_state": "deployed",
                    "last_date": "2020-09-13 22:32:04",
                    "nfs_boot_conf": 2.0,
                    "nfs_boot_off": 5.0,
                    "nfs_boot_on": 8.0,
                    "env_copy": 36.0,
                    "env_check": 197.0,
                    "delete_partition": 16.0,
                    "create_partition": 11.0,
                    "mount_partition": 14.0,
                    "resize_partition": 14.0,
                    "wait_resizing": 10.0,
                    "system_conf": 30.0,
                    "user_conf": 62.0,
                    "user_script": 72.0
                },
                "total": 477.0,
                "ping": true,
                "ssh": true,
                "init_script": true
            }
        ],
        "node-5": [
            {
                "ip": "192.168.1.55",
                "start_date": "2020-09-13 22:24:07.600149",
                "states": {
                    "last_state": "deployed",
                    "last_date": "2020-09-13 22:32:04",
                    "nfs_boot_conf": 2.0,
                    "nfs_boot_off": 5.0,
                    "nfs_boot_on": 8.0,
                    "env_copy": 37.0,
                    "env_check": 197.0,
                    "delete_partition": 16.0,
                    "create_partition": 12.0,
                    "mount_partition": 13.0,
                    "resize_partition": 14.0,
                    "wait_resizing": 9.0,
                    "system_conf": 42.0,
                    "user_conf": 51.0,
                    "user_script": 71.0
                },
                "total": 477.0,
                "ping": true,
                "ssh": true,
                "init_script": true
            }
        ],
        "node-6": [
            {
                "ip": "192.168.1.56",
                "start_date": "2020-09-13 22:24:07.600502",
                "states": {
                    "last_state": "deployed",
                    "last_date": "2020-09-13 22:32:25",
                    "nfs_boot_conf": 2.0,
                    "nfs_boot_off": 5.0,
                    "nfs_boot_on": 9.0,
                    "env_copy": 58.0,
                    "env_check": 194.0,
                    "delete_partition": 14.0,
                    "create_partition": 13.0,
                    "mount_partition": 12.0,
                    "resize_partition": 8.0,
                    "wait_resizing": 80.0,
                    "system_conf": 46.0,
                    "user_conf": 49.0,
                    "user_script": 8.0
                },
                "total": 498.0,
                "ping": true,
                "ssh": true,
                "init_script": true
            }
        ],
        "node-7": [
            {
                "ip": "192.168.1.57",
                "start_date": "2020-09-13 22:24:07.600851",
                "states": {
                    "last_state": "deployed",
                    "last_date": "2020-09-13 22:32:37",
                    "nfs_boot_conf": 2.0,
                    "nfs_boot_off": 6.0,
                    "nfs_boot_on": 8.0,
                    "env_copy": 59.0,
                    "env_check": 193.0,
                    "delete_partition": 15.0,
                    "create_partition": 14.0,
                    "mount_partition": 10.0,
                    "resize_partition": 8.0,
                    "wait_resizing": 80.0,
                    "system_conf": 59.0,
                    "user_conf": 50.0,
                    "user_script": 6.0
                },
                "total": 510.0,
                "ping": true,
                "ssh": true,
                "init_script": true
            }
        ],
        "node-8": [
            {
                "ip": "192.168.1.58",
                "start_date": "2020-09-13 22:24:07.601199",
                "states": {
                    "last_state": "deployed",
                    "last_date": "2020-09-13 22:32:05",
                    "nfs_boot_conf": 2.0,
                    "nfs_boot_off": 6.0,
                    "nfs_boot_on": 9.0,
                    "env_copy": 35.0,
                    "env_check": 201.0,
                    "delete_partition": 12.0,
                    "create_partition": 13.0,
                    "mount_partition": 13.0,
                    "resize_partition": 13.0,
                    "wait_resizing": 9.0,
                    "system_conf": 54.0,
                    "user_conf": 39.0,
                    "user_script": 72.0
                },
                "total": 478.0,
                "ping": true,
                "ssh": true,
                "init_script": true
            }
        ],
        "node-10": [
            {
                "ip": "192.168.1.60",
                "start_date": "2020-09-13 22:24:07.601555",
                "states": {
                    "last_state": "deployed",
                    "last_date": "2020-09-13 22:32:16",
                    "nfs_boot_conf": 2.0,
                    "nfs_boot_off": 6.0,
                    "nfs_boot_on": 9.0,
                    "env_copy": 36.0,
                    "env_check": 200.0,
                    "delete_partition": 13.0,
                    "create_partition": 13.0,
                    "mount_partition": 12.0,
                    "resize_partition": 13.0,
                    "wait_resizing": 10.0,
                    "system_conf": 70.0,
                    "user_conf": 96.0,
                    "user_script": 9.0
                },
                "total": 489.0,
                "ping": true,
                "ssh": true,
                "init_script": true
            }
        ],
        "node-11": [
            {
                "ip": "192.168.1.61",
                "start_date": "2020-09-13 22:24:07.601890",
                "states": {
                    "last_state": "deployed",
                    "last_date": "2020-09-13 22:32:37",
                    "nfs_boot_conf": 2.0,
                    "nfs_boot_off": 7.0,
                    "nfs_boot_on": 9.0,
                    "env_copy": 57.0,
                    "env_check": 194.0,
                    "delete_partition": 15.0,
                    "create_partition": 14.0,
                    "mount_partition": 10.0,
                    "resize_partition": 8.0,
                    "wait_resizing": 80.0,
                    "system_conf": 63.0,
                    "user_conf": 46.0,
                    "user_script": 5.0
                },
                "total": 510.0,
                "ping": true,
                "ssh": true,
                "init_script": true
            }
        ],
        "node-12": [
            {
                "ip": "192.168.1.62",
                "start_date": "2020-09-13 22:24:07.602221",
                "states": {
                    "last_state": "deployed",
                    "last_date": "2020-09-13 22:32:46",
                    "nfs_boot_conf": 2.0,
                    "nfs_boot_off": 7.0,
                    "nfs_boot_on": 9.0,
                    "env_copy": 60.0,
                    "env_check": 191.0,
                    "delete_partition": 15.0,
                    "create_partition": 15.0,
                    "mount_partition": 10.0,
                    "resize_partition": 7.0,
                    "wait_resizing": 80.0,
                    "system_conf": 75.0,
                    "user_conf": 44.0,
                    "user_script": 4.0
                },
                "total": 519.0,
                "ping": true,
                "ssh": true,
                "init_script": true
            }
        ],
        "node-13": [
            {
                "ip": "192.168.1.63",
                "start_date": "2020-09-13 22:24:07.602554",
                "states": {
                    "last_state": "deployed",
                    "last_date": "2020-09-13 22:32:17",
                    "nfs_boot_conf": 2.0,
                    "nfs_boot_off": 7.0,
                    "nfs_boot_on": 10.0,
                    "env_copy": 46.0,
                    "env_check": 192.0,
                    "delete_partition": 9.0,
                    "create_partition": 15.0,
                    "mount_partition": 11.0,
                    "resize_partition": 13.0,
                    "wait_resizing": 9.0,
                    "system_conf": 76.0,
                    "user_conf": 93.0,
                    "user_script": 7.0
                },
                "total": 490.0,
                "ping": true,
                "ssh": true,
                "init_script": true
            }
        ]
    }
}