{
    "raspbian_buster_32bit": {
        "node-1": [
            {
                "ip": "192.168.1.110",
                "start_date": "2020-12-16 22:00:24.215386",
                "states": {
                    "last_state": "deployed",
                    "last_date": "2020-12-16 22:06:07",
                    "nfs_boot_conf": 2.0,
                    "nfs_boot_off": 4.0,
                    "nfs_boot_on": 5.0,
                    "env_copy": 42.0,
                    "env_check": 180.0,
                    "delete_partition": 6.0,
                    "create_partition": 6.0,
                    "mount_partition": 6.0,
                    "resize_partition": 5.0,
                    "wait_resizing": 19.0,
                    "system_conf": 10.0,
                    "user_conf": 47.0,
                    "user_script": 11.0
                },
                "total": 343.0,
                "ping": true,
                "ssh": true,
                "init_script": true
            }
        ],
        "node-2": [
            {
                "ip": "192.168.1.111",
                "start_date": "2020-12-16 22:00:24.215750",
                "states": {
                    "last_state": "deployed",
                    "last_date": "2020-12-16 22:06:02",
                    "nfs_boot_conf": 2.0,
                    "nfs_boot_off": 4.0,
                    "nfs_boot_on": 5.0,
                    "env_copy": 43.0,
                    "env_check": 180.0,
                    "delete_partition": 5.0,
                    "create_partition": 7.0,
                    "mount_partition": 6.0,
                    "resize_partition": 5.0,
                    "wait_resizing": 18.0,
                    "system_conf": 18.0,
                    "user_conf": 40.0,
                    "user_script": 5.0
                },
                "total": 338.0,
                "ping": true,
                "ssh": true,
                "init_script": true
            }
        ],
        "node-3": [
            {
                "ip": "192.168.1.112",
                "start_date": "2020-12-16 22:00:24.216057",
                "states": {
                    "last_state": "deployed",
                    "last_date": "2020-12-16 22:05:55",
                    "nfs_boot_conf": 2.0,
                    "nfs_boot_off": 4.0,
                    "nfs_boot_on": 6.0,
                    "env_copy": 36.0,
                    "env_check": 180.0,
                    "delete_partition": 5.0,
                    "create_partition": 5.0,
                    "mount_partition": 6.0,
                    "resize_partition": 7.0,
                    "wait_resizing": 5.0,
                    "system_conf": 18.0,
                    "user_conf": 52.0,
                    "user_script": 5.0
                },
                "total": 331.0,
                "ping": true,
                "ssh": true,
                "init_script": true
            }
        ],
        "node-4": [
            {
                "ip": "192.168.1.113",
                "start_date": "2020-12-16 22:00:24.216364",
                "states": {
                    "last_state": "deployed",
                    "last_date": "2020-12-16 22:06:08",
                    "nfs_boot_conf": 2.0,
                    "nfs_boot_off": 5.0,
                    "nfs_boot_on": 5.0,
                    "env_copy": 43.0,
                    "env_check": 179.0,
                    "delete_partition": 6.0,
                    "create_partition": 7.0,
                    "mount_partition": 5.0,
                    "resize_partition": 5.0,
                    "wait_resizing": 18.0,
                    "system_conf": 23.0,
                    "user_conf": 41.0,
                    "user_script": 5.0
                },
                "total": 344.0,
                "ping": true,
                "ssh": true,
                "init_script": true
            }
        ]
    }
}